hookmaster/__init__.py
hookmaster/__main__.py
hookmaster/cli.py
hookmaster-1.4.5.dist-info/licenses/LICENSE
hookmaster-1.4.5.dist-info/METADATA
hookmaster-1.4.5.dist-info/WHEEL
hookmaster-1.4.5.dist-info/entry_points.txt
hookmaster-1.4.5.dist-info/top_level.txt
hookmaster-1.4.5.dist-info/RECORD
