Metadata-Version: 2.4
Name: hookmaster
Version: 1.4.5
Summary: hookmaster
Classifier: Operating System :: OS Independent
Classifier: Programming Language :: Python
Classifier: Programming Language :: Python :: 3.10
Classifier: Programming Language :: Python :: 3.11
Classifier: Programming Language :: Python :: 3.12
Classifier: Programming Language :: Python :: 3.13
Classifier: Programming Language :: Python :: 3.14
Requires-Python: >=3.10
License-File: LICENSE
Requires-Dist: tomli>=1.1.0; python_version < "3.11"
Dynamic: license-file
